substitute/__init__.py
substitute/complaint.py
substitute/messages.py
substitute/substitute.py
substitute3-1.3.1.dist-info/LICENSE
substitute3-1.3.1.dist-info/METADATA
substitute3-1.3.1.dist-info/WHEEL
substitute3-1.3.1.dist-info/top_level.txt
substitute3-1.3.1.dist-info/RECORD
