Metadata-Version: 2.2
Name: substitute3
Version: 1.3.1
Summary: A friendly substitute for python mocking frameworks
Home-page: https://github.com/Marcurion/substitute3
Author: Original: Johannes Hofmeister
Author-email: substitute@spam.cessor.de
Keywords: mock,stub,fake,test,testing,tdd,bdd,substitute,substitution,replacement,unittesting
Requires-Python: >=3.11.11
License-File: LICENSE
Dynamic: author
Dynamic: author-email
Dynamic: description
Dynamic: description-content-type
Dynamic: home-page
Dynamic: keywords
Dynamic: requires-python
Dynamic: summary
